secondary.py
secondary-1.0.dist-info/WHEEL
secondary-1.0.dist-info/METADATA
secondary-1.0.dist-info/RECORD
